{
    "apk_version": "https://pkg.biligame.com/games/blhx_9.6.11_0814_1_20250819_110937_2a0c3.apk",
    "hashfile_url": {
        "az": "$azhash$9$6$334$1258e2cedfdeb7d2",
        "cv": "$cvhash$1256$bf80f66832e04576",
        "l2d": "$l2dhash$1297$a38e57d5b959cf2c",
        "pic": "$pichash$1201$b2fa6e317482e25f",
        "bgm": "$bgmhash$1201$b2fa6e317482e25f",
        "painting": "$paintinghash$1386$cf843ed45c4240bc",
        "manga": "$mangahash$1212$85edaa2ad37f9bb4",
        "cipher": "$cipherhash$1206$5df397233956c99e",
        "dorm": "$dormhash$1360$321046fdc387639f",
        "map": "$maphash$151$fc9dfee61fbe62e4"
    }
}